Workbook

Sheet Sheet2
A1: c | B1: Gender | C1: Income(Per Month) | D1: In general, how would your best friend describe you as a risk taker? | E1: You are on a TV game show and can choose one of the following; which would you take? | F1: You have just finished saving for a “once-in-a-lifetime” vacation. Three weeks before you plan to leave, you lose your job. You would: | G1: If you unexpectedly received $20,000 to invest, what would you do? | H1: In terms of experience, how comfortable are you investing in stocks or stock mutual funds? | I1: When you think of the word “risk,” which of the following words comes to mind first? | J1: Some experts are predicting prices of assets such as gold, jewels, collectibles, and real estate (hard assets) to increase in value; bond prices may fall, however, experts tend to agree that government bonds are relatively safe. Most of your investment assets are now in high-interest government bonds. What would you do? | K1: Given the best and worst case returns of the four investment choices below, which would you prefer? | L1: In addition to whatever you own, you have been given $1,000. You are now asked to choose between: | M1: In addition to whatever you own, you have been given $2,000. You are now asked to choose between | N1: Suppose a relative left you an inheritance of $100,000, stipulating in the will that you invest ALL the money in ONE of the following choices. Which one would you select? | O1: If you had to invest $20,000, which of the following investment choices would you find most appealing? | P1: Your trusted friend and neighbor, an experienced geologist, is putting together a group of investors to fund an exploratory gold mining venture. The venture could pay back 50 to 100 times the investment if successful. If the mine is a bust, the entire investment is worthless. Your friend estimates the chance of success is only 20%. If you had the money, how much would you invest?
A2: <18-30 | B2: Male | C2: <10k-20k | D2: Willing to take risks after completing adequate research | E2: A 50% chance at winning $5,000 | F2: Take a much more modest vacation | G2: Invest it in safe high-quality bonds or bond mutual funds | H2: Somewhat comfortable | I2: Uncertainty | J2: Sell the bonds, put half the proceeds into money market accounts, and the other half into hard assets | K2: $800 gain best case, $200 loss worst case | L2: A 50% chance to gain $1,000 and a 50% chance to gain nothing. | M2: A 50% chance to lose $1,000 and a 50% chance to lose nothing. | N2: A mutual fund that owns stocks and bonds | O2: 30% in low-risk investments, 40% in medium-risk investments, 30% in high-risk investments | P2: One month’s salary
A3: <18-30 | B3: Male | C3: <10k-20k | D3: Willing to take risks after completing adequate research | E3: $1,000 in cash | F3: Take a much more modest vacation | G3: Invest it in safe high-quality bonds or bond mutual funds | H3: Somewhat comfortable | I3: Uncertainty | J3: Sell the bonds, put half the proceeds into money market accounts, and the other half into hard assets | K3: $800 gain best case, $200 loss worst case | L3: A sure gain of $500 | M3: A 50% chance to lose $1,000 and a 50% chance to lose nothing. | N3: A mutual fund that owns stocks and bonds | O3: 30% in low-risk investments, 40% in medium-risk investments, 30% in high-risk investments | P3: One month’s salary
A4: <18-30 | B4: Male | C4: <10k-20k | D4: Willing to take risks after completing adequate research | E4: $1,000 in cash | F4: Take a much more modest vacation | G4: Invest it in safe high-quality bonds or bond mutual funds | H4: Somewhat comfortable | I4: Uncertainty | J4: Sell the bonds, put half the proceeds into money market accounts, and the other half into hard assets | K4: $800 gain best case, $200 loss worst case | L4: A 50% chance to gain $1,000 and a 50% chance to gain nothing. | M4: A 50% chance to lose $1,000 and a 50% chance to lose nothing. | N4: A mutual fund that owns stocks and bonds | O4: 30% in low-risk investments, 40% in medium-risk investments, 30% in high-risk investments | P4: One month’s salary
A5: <18-30 | B5: Male | C5: <10k-20k | D5: Willing to take risks after completing adequate research | E5: $1,000 in cash | F5: Take a much more modest vacation | G5: Invest it in stocks or stock mutual funds | H5: Not at all comfortable | I5: Uncertainty | J5: Hold the bonds | K5: $2,600 gain best case, $800 loss worst case | L5: A 50% chance to gain $1,000 and a 50% chance to gain nothing. | M5: A 50% chance to lose $1,000 and a 50% chance to lose nothing. | N5: Commodities like gold, silver, and oil | O5: 30% in low-risk investments, 40% in medium-risk investments, 30% in high-risk investments | P5: One month’s salary
A6: 31-40 | B6: Female | C6: <10k-20k | D6: Willing to take risks after completing adequate research | E6: A 50% chance at winning $5,000 | F6: Take a much more modest vacation | G6: Invest it in safe high-quality bonds or bond mutual funds | H6: Somewhat comfortable | I6: Uncertainty | J6: Sell the bonds, put half the proceeds into money market accounts, and the other half into hard assets | K6: $800 gain best case, $200 loss worst case | L6: A 50% chance to gain $1,000 and a 50% chance to gain nothing. | M6: A 50% chance to lose $1,000 and a 50% chance to lose nothing. | N6: A portfolio of 15 common stocks | O6: 30% in low-risk investments, 40% in medium-risk investments, 30% in high-risk investments | P6: One month’s salary
A7: <18-30 | B7: Female | C7: <10k-20k | D7: A real gambler | E7: A 5% chance at winning $100,000 | F7: Take a much more modest vacation | G7: Deposit it in a bank account, money market account, or insured CD | H7: Not at all comfortable | I7: Opportunity | J7: Hold the bonds | K7: $200 gain best case; $0 gain/loss worst case | L7: A 50% chance to gain $1,000 and a 50% chance to gain nothing. | M7: A sure loss of $500 | N7: A savings account or money market mutual fund | O7: 10% in low-risk investments, 40% in medium-risk investments, 50% in high-risk investments | P7: One month’s salary
A8: <18-30 | B8: Female | C8: <10k-20k | D8: Willing to take risks after completing adequate research | E8: A 25% chance at winning $10,000 | F8: Take a much more modest vacation | G8: Invest it in stocks or stock mutual funds | H8: Somewhat comfortable | I8: Opportunity | J8: Sell the bonds, put half the proceeds into money market accounts, and the other half into hard assets | K8: $2,600 gain best case, $800 loss worst case | L8: A 50% chance to gain $1,000 and a 50% chance to gain nothing. | M8: A 50% chance to lose $1,000 and a 50% chance to lose nothing. | N8: Commodities like gold, silver, and oil | O8: 30% in low-risk investments, 40% in medium-risk investments, 30% in high-risk investments | P8: One month’s salary
A9: <18-30 | B9: Female | C9: 51k-60k> | D9: Willing to take risks after completing adequate research | E9: A 5% chance at winning $100,000 | F9: Go as scheduled, reasoning that you need the time to prepare for a job search | G9: Invest it in stocks or stock mutual funds | H9: Very Comfortable | I9: Uncertainty | J9: Sell the bonds and put the total proceeds into hard assets | K9: $200 gain best case; $0 gain/loss worst case | L9: A sure gain of $500 | M9: A 50% chance to lose $1,000 and a 50% chance to lose nothing. | N9: A savings account or money market mutual fund | O9: 60% in low-risk investments, 30% in medium-risk investments, 10% in high-risk investments | P9: One month’s salary
A10: <18-30 | B10: Male | C10: <10k-20k | D10: A real gambler | E10: $1,000 in cash | F10: Go as scheduled, reasoning that you need the time to prepare for a job search | G10: Deposit it in a bank account, money market account, or insured CD | H10: Very Comfortable | I10: Opportunity | J10: Sell the bonds and put the total proceeds into hard assets | K10: $2,600 gain best case, $800 loss worst case | L10: A sure gain of $500 | M10: A sure loss of $500 | N10: A portfolio of 15 common stocks | O10: 30% in low-risk investments, 40% in medium-risk investments, 30% in high-risk investments | P10: One month’s salary
A11: <18-30 | B11: Male | C11: <10k-20k | D11: A real risk avoider | E11: A 50% chance at winning $5,000 | F11: Take a much more modest vacation | G11: Deposit it in a bank account, money market account, or insured CD | H11: Somewhat comfortable | I11: Uncertainty | J11: Sell the bonds, put half the proceeds into money market accounts, and the other half into hard assets | K11: $800 gain best case, $200 loss worst case | L11: A 50% chance to gain $1,000 and a 50% chance to gain nothing. | M11: A 50% chance to lose $1,000 and a 50% chance to lose nothing. | N11: A portfolio of 15 common stocks | O11: 30% in low-risk investments, 40% in medium-risk investments, 30% in high-risk investments | P11: One month’s salary
A12: <18-30 | B12: Female | C12: 51k-60k> | D12: Willing to take risks after completing adequate research | E12: A 5% chance at winning $100,000 | F12: Go as scheduled, reasoning that you need the time to prepare for a job search | G12: Invest it in safe high-quality bonds or bond mutual funds | H12: Very Comfortable | I12: Uncertainty | J12: Sell the bonds, put half the proceeds into money market accounts, and the other half into hard assets | K12: $200 gain best case; $0 gain/loss worst case | L12: A sure gain of $500 | M12: A 50% chance to lose $1,000 and a 50% chance to lose nothing. | N12: A savings account or money market mutual fund | O12: 60% in low-risk investments, 30% in medium-risk investments, 10% in high-risk investments | P12: One month’s salary
... A46: <18-30 | B46: Male | C46: <10k-20k | D46: a real risk avoider | E46: $1000 in cash | F46: Cancel the vacation | G46: Deposit it in a bank account, money market account, or insured CD | H46: Not at all comfortable | I46: Loss | J46: Hold the bonds | K46: $800 gain best case; $200 loss worst case | L46: A sure gain of $500 | M46: A sure loss of $500 | N46: A mutual fund that owns stocks and bonds | O46: 60% low-risk, 30% medium-risk, 10% high-risk | P46: Nothing
A47: <18-30 | B47: Male | C47: <10k-20k | E47: A 50% chance at winning $5,000 | F47: Extend your vacation, because this might be your last chance to go first-class | G47: Invest it in safe high-quality bonds or bond mutual funds | H47: Somewhat comfortable | I47: Uncertainty | J47: Sell the bonds, put half the proceeds into money market accounts, and the other half into hard assets | K47: $2,600 gain best case; $800 loss worst case | L47: A sure gain of $500 | M47: A 50% chance to lose $1,000 and a 50% chance to lose nothing | N47: A savings account or money market mutual fund | O47: 30% low-risk, 40% medium-risk, 30% high-risk | P47: Three months’ salary
A48: <18-30 | B48: Female | C48: <10k-20k | D48: Willing to take risks after completing adequate research | E48: A 50% chance at winning $5,000 | F48: Take a much more modest vacation | G48: Invest it in safe high-quality bonds or bond mutual funds | H48: Somewhat comfortable | I48: Thrill | J48: Sell the bonds, put half the proceeds into money market accounts, and the other half into hard assets | K48: $2,600 gain best case; $800 loss worst case | L48: A sure gain of $500 | M48: A 50% chance to lose $1,000 and a 50% chance to lose nothing | N48: A mutual fund that owns stocks and bonds | O48: 30% low-risk, 40% medium-risk, 30% high-risk | P48: One month’s salary
A49: <18-30 | B49: Male | C49: 21k-40k | D49: a real gambler | E49: A 50% chance at winning $5,000 | F49: Take a much more modest vacation | G49: Deposit it in a bank account, money market account, or insured CD | H49: Somewhat comfortable | I49: Uncertainty | J49: Sell the bonds, put half the proceeds into money market accounts, and the other half into hard assets | K49: $800 gain best case; $200 loss worst case | L49: A sure gain of $500 | M49: A sure loss of $500 | N49: A savings account or money market mutual fund | O49: 30% low-risk, 40% medium-risk, 30% high-risk | P49: One month’s salary
A50: 41-50 | B50: Male | C50: 21k-40k | D50: Willing to take risks after completing adequate research | E50: A 50% chance at winning $5,000 | F50: Take a much more modest vacation | G50: Deposit it in a bank account, money market account, or insured CD | H50: Somewhat comfortable | I50: Uncertainty | J50: Sell the bonds and put the total proceeds into hard assets | K50: $800 gain best case; $200 loss worst case | L50: A 50% chance to gain $1,000 and a 50% chance to gain nothing | M50: A 50% chance to lose $1,000 and a 50% chance to lose nothing | N50: A portfolio of 15 common stocks | O50: 30% low-risk, 40% medium-risk, 30% high-risk | P50: One month’s salary
A51: <18-30 | B51: Male | C51: <10k-20k | D51: a real risk avoider | E51: $1000 in cash | F51: Go as scheduled, reasoning that you need the time to prepare for a job search | G51: Deposit it in a bank account, money market account, or insured CD | H51: Not at all comfortable | I51: Thrill | J51: Sell the bonds, put half the proceeds into money market accounts, and the other half into hard assets | K51: $200 gain best case; $0 gain/loss worst case | L51: A sure gain of $500 | M51: A 50% chance to lose $1,000 and a 50% chance to lose nothing | N51: A savings account or money market mutual fund | O51: 60% low-risk, 30% medium-risk, 10% high-risk | P51: Nothing
A52: <18-30 | B52: Female | C52: <10k-20k | D52: a real risk avoider | E52: $1000 in cash | F52: Cancel the vacation | G52: Invest it in safe high-quality bonds or bond mutual funds | H52: Not at all comfortable | I52: Thrill | J52: Sell the bonds and put the total proceeds into hard assets | K52: $2,600 gain best case; $800 loss worst case | L52: A sure gain of $500 | M52: A 50% chance to lose $1,000 and a 50% chance to lose nothing | N52: A mutual fund that owns stocks and bonds | O52: 30% low-risk, 40% medium-risk, 30% high-risk | P52: One month’s salary
A53: 31-40 | B53: Female | C53: 21k-40k | D53: cautious | E53: A 50% chance at winning $5,000 | F53: Take a much more modest vacation | G53: Invest it in safe high-quality bonds or bond mutual funds | H53: Not at all comfortable | I53: Opportunity | J53: Sell the bonds and put the total proceeds into hard assets | K53: $2,600 gain best case; $800 loss worst case | L53: A sure gain of $500 | M53: A sure loss of $500 | N53: A portfolio of 15 common stocks | O53: 30% low-risk, 40% medium-risk, 30% high-risk | P53: Nothing
A54: 41-50 | B54: Female | C54: 21k-40k | D54: Willing to take risks after completing adequate research | E54: A 25% chance at winning $10,000 | F54: Go as scheduled, reasoning that you need the time to prepare for a job search | G54: Deposit it in a bank account, money market account, or insured CD | H54: Very comfortable | I54: Loss | J54: Sell the bonds, put half the proceeds into money market accounts, and the other half into hard assets | K54: $2,600 gain best case; $800 loss worst case | L54: A 50% chance to gain $1,000 and a 50% chance to gain nothing | M54: A sure loss of $500 | N54: A mutual fund that owns stocks and bonds | O54: 30% low-risk, 40% medium-risk, 30% high-risk | P54: Three months’ salary
A55: <18-30 | B55: Male | C55: 21k-40k | D55: cautious | E55: A 25% chance at winning $10,000 | F55: Take a much more modest vacation | G55: Invest it in stocks or stock mutual funds | H55: Somewhat comfortable | I55: Opportunity | J55: Sell the bonds, put all the money into hard assets, and borrow additional money to buy more | K55: $800 gain best case; $200 loss worst case | L55: A 50% chance to gain $1,000 and a 50% chance to gain nothing | M55: A sure loss of $500 | N55: A savings account or money market mutual fund | O55: 10% low-risk, 40% medium-risk, 50% high-risk | P55: Nothing
A56: 51->60 | B56: Male | C56: 41k-60k | D56: a real gambler | E56: A 5% chance at winning $100,000 | F56: Go as scheduled, reasoning that you need the time to prepare for a job search | G56: Invest it in safe high-quality bonds or bond mutual funds | H56: Very comfortable | I56: Thrill | J56: Sell the bonds and put the total proceeds into hard assets | K56: $4,800 gain best case; $2,400 loss worst case | L56: A 50% chance to gain $1,000 and a 50% chance to gain nothing | M56: A sure loss of $500 | N56: Commodities like gold, silver, and oil | O56: 10% low-risk, 40% medium-risk, 50% high-risk | P56: Six months’ salary
A57: 51->60 | B57: Female | C57: >60k | D57: a real gambler | E57: A 5% chance at winning $100,000 | F57: Extend your vacation, because this might be your last chance to go first-class | G57: Invest it in safe high-quality bonds or bond mutual funds | H57: Very comfortable | I57: Opportunity | J57: Sell the bonds, put half the proceeds into money market accounts, and the other half into hard assets | K57: $4,800 gain best case; $2,400 loss worst case | L57: A 50% chance to gain $1,000 and a 50% chance to gain nothing | M57: A 50% chance to lose $1,000 and a 50% chance to lose nothing | N57: A mutual fund that owns stocks and bonds | O57: 10% low-risk, 40% medium-risk, 50% high-risk | P57: Six months’ salary
A58: 31-40 | B58: Female | C58: 21k-40k | D58: cautious | E58: A 25% chance at winning $10,000 | F58: Cancel the vacation | G58: Invest it in safe high-quality bonds or bond mutual funds | H58: Not at all comfortable | I58: Thrill | J58: Sell the bonds, put half the proceeds into money market accounts, and the other half into hard assets | K58: $2,600 gain best case; $800 loss worst case | L58: A 50% chance to gain $1,000 and a 50% chance to gain nothing | M58: A sure loss of $500 | N58: A portfolio of 15 common stocks | O58: 30% low-risk, 40% medium-risk, 30% high-risk | P58: One month’s salary
A59: 51->60 | B59: Male | C59: 41k-60k | D59: Willing to take risks after completing adequate research | E59: A 50% chance at winning $5,000 | F59: Go as scheduled, reasoning that you need the time to prepare for a job search | G59: Deposit it in a bank account, money market account, or insured CD | H59: Somewhat comfortable | I59: Opportunity | J59: Sell the bonds and put the total proceeds into hard assets | K59: $800 gain best case; $200 loss worst case | L59: A 50% chance to gain $1,000 and a 50% chance to gain nothing | M59: A sure loss of $500 | O59: 30% low-risk, 40% medium-risk, 30% high-risk | P59: Three months’ salary
A60: <18-30 | B60: Female | C60: <10k-20k | D60: a real gambler | E60: A 25% chance at winning $10,000 | F60: Go as scheduled, reasoning that you need the time to prepare for a job search | G60: Invest it in safe high-quality bonds or bond mutual funds | H60: Not at all comfortable | I60: Loss | J60: Sell the bonds and put the total proceeds into hard assets | K60: $2,600 gain best case; $800 loss worst case | L60: A sure gain of $500 | M60: A 50% chance to lose $1,000 and a 50% chance to lose nothing | N60: A portfolio of 15 common stocks | O60: 30% low-risk, 40% medium-risk, 30% high-risk | P60: Three months’ salary
A61: 41-50 | B61: Male | C61: 41k-60k | D61: a real risk avoider | E61: A 25% chance at winning $10,000 | F61: Go as scheduled, reasoning that you need the time to prepare for a job search | G61: Deposit it in a bank account, money market account, or insured CD | H61: Somewhat comfortable | I61: Thrill | J61: Sell the bonds and put the total proceeds into hard assets | K61: $800 gain best case; $200 loss worst case | L61: A 50% chance to gain $1,000 and a 50% chance to gain nothing | M61: A 50% chance to lose $1,000 and a 50% chance to lose nothing | N61: A portfolio of 15 common stocks | O61: 30% low-risk, 40% medium-risk, 30% high-risk | P61: Six months’ salary
A62: 41-50 | B62: Male | C62: 21k-40k | D62: Willing to take risks after completing adequate research | E62: A 50% chance at winning $5,000 | G62: Deposit it in a bank account, money market account, or insured CD | H62: Not at all comfortable | I62: Uncertainty | J62: Sell the bonds and put the total proceeds into hard assets | K62: $800 gain best case; $200 loss worst case | L62: A 50% chance to gain $1,000 and a 50% chance to gain nothing | M62: A sure loss of $500 | N62: A portfolio of 15 common stocks | O62: 30% low-risk, 40% medium-risk, 30% high-risk | P62: Nothing
A63: <18-30 | B63: Female | C63: <10k-20k | D63: a real gambler | E63: $1000 in cash | F63: Go as scheduled, reasoning that you need the time to prepare for a job search | G63: Deposit it in a bank account, money market account, or insured CD | H63: Not at all comfortable | I63: Opportunity | J63: Sell the bonds, put half the proceeds into money market accounts, and the other half into hard assets | K63: $800 gain best case; $200 loss worst case | L63: A 50% chance to gain $1,000 and a 50% chance to gain nothing | M63: A sure loss of $500 | N63: A savings account or money market mutual fund | O63: 60% low-risk, 30% medium-risk, 10% high-risk | P63: One month’s salary
A64: <18-30 | B64: Male | C64: 21k-40k | F64: Cancel the vacation | G64: Deposit it in a bank account, money market account, or insured CD | H64: Not at all comfortable | I64: Loss | J64: Hold the bonds
A65: <18-30 | B65: Male | C65: <10k-20k | D65: a real gambler | E65: A 50% chance at winning $5,000 | F65: Take a much more modest vacation | G65: Invest it in safe high-quality bonds or bond mutual funds | H65: Not at all comfortable | I65: Uncertainty | J65: Hold the bonds | K65: $800 gain best case; $200 loss worst case | L65: A 50% chance to gain $1,000 and a 50% chance to gain nothing | M65: A 50% chance to lose $1,000 and a 50% chance to lose nothing | N65: A portfolio of 15 common stocks | O65: 30% low-risk, 40% medium-risk, 30% high-risk | P65: Nothing
A66: <18-30 | B66: Female | C66: <10k-20k
A67: <18-30 | B67: Male | C67: >60k | D67: a real gambler | E67: A 5% chance at winning $100,000 | F67: Cancel the vacation | G67: Invest it in safe high-quality bonds or bond mutual funds | H67: Very comfortable | I67: Opportunity | J67: Sell the bonds and put the total proceeds into hard assets | K67: $4,800 gain best case; $2,400 loss worst case | L67: A 50% chance to gain $1,000 and a 50% chance to gain nothing | M67: A 50% chance to lose $1,000 and a 50% chance to lose nothing | N67: A portfolio of 15 common stocks | O67: 30% low-risk, 40% medium-risk, 30% high-risk | P67: One month’s salary

Sheet Sheet5
A1: t-Test: Two-Sample Assuming Unequal Variances
B3: female | C3: male
A4: Mean | B4: 27.2 | C4: 28.176471
A5: Variance | B5: 52.924138 | C5: 50.937611
A6: Observations | B6: 30 | C6: 34
A7: Hypothesized Mean Difference | B7: 0
A8: df | B8: 61
A9: t Stat | B9: -0.54062612
A10: P(T<=t) one-tail | B10: 0.295367
A11: t Critical one-tail | B11: 1.6702195
A12: P(T<=t) two-tail | B12: 0.590734
A13: t Critical two-tail | B13: 1.9996236
A17: age group | B17: Count | C17: Mean Risk Score | D17: Standard Deviation | E17: F-statistic | F17: P-value
A18: 51->60 | B18: 5 | C18: 35.4 | D18: 6.11 | E18: 2.5278 | F18: 0.0655
A19: 41-50 | B19: 6 | C19: 29 | D19: 6.57
A20: 31-40 | B20: 11 | C20: 28 | D20: 5.8
A21: <18-30 | B21: 44 | C21: 26.68 | D21: 7.13
A24: Income Level | B24: Count | C24: Mean Risk Score | D24: Standard Deviation | E24: F-statistic | F24: P-value
A25: >60k | B25: 3 | C25: 37.67 | D25: 3.06 | E25: 2.4562 | F25: 0.055
A26: 41k-60k | B26: 5 | C26: 32.2 | D26: 8.5
A27: 51k-60k> | B27: 2 | C27: 29 | D27: 1.41
A28: <10k-20k | B28: 39 | C28: 26.92 | D28: 6.46
A29: 21k-40k | B29: 17 | C29: 26.53 | D29: 7.48

Sheet Sheet6
A1: Anova: Single Factor
A3: SUMMARY
A4: Groups | B4: Count | C4: Sum | D4: Average | E4: Variance
A5: You have just finished saving for a “once-in-a-lifetime” vacation. Three weeks before you plan to leave, you lose your job. You would: | B5: 64 | C5: 151 | D5: 2.359375 | E5: 0.77356151
A6: If you unexpectedly received $20,000 to invest, what would you do? | B6: 65 | C6: 119 | D6: 1.8307692 | E6: 0.51778846
A7: In terms of experience, how comfortable are you investing in stocks or stock mutual funds? | B7: 65 | C7: 122 | D7: 1.8769231 | E7: 0.51586538
A8: When you think of the word “risk,” which of the following words comes to mind first? | B8: 65 | C8: 162 | D8: 2.4923077 | E8: 0.81634615
A9: Some experts are predicting prices of assets such as gold, jewels, collectibles, and real estate (hard assets) to increase in value; bond prices may fall, however, experts tend to agree that government bonds are relatively safe. Most of your investment assets are now in high-interest government bonds. What would you do? | B9: 65 | C9: 145 | D9: 2.2307692 | E9: 0.71153846
A10: Given the best and worst case returns of the four investment choices below, which would you prefer? | B10: 64 | C10: 149 | D10: 2.328125 | E10: 0.9858631
A11: In addition to whatever you own, you have been given $1,000. You are now asked to choose between: | B11: 64 | C11: 132 | D11: 2.0625 | E11: 1.0119048
A12: In addition to whatever you own, you have been given $2,000. You are now asked to choose between | B12: 64 | C12: 144 | D12: 2.25 | E12: 0.95238095
A13: Suppose a relative left you an inheritance of $100,000, stipulating in the will that you invest ALL the money in ONE of the following choices. Which one would you select? | B13: 63 | C13: 141 | D13: 2.2380952 | E13: 0.99078341
A14: If you had to invest $20,000, which of the following investment choices would you find most appealing? | B14: 64 | C14: 118 | D14: 1.84375 | E14: 0.32440476
A15: Your trusted friend and neighbor, an experienced geologist, is putting together a group of investors to fund an exploratory gold mining venture. The venture could pay back 50 to 100 times the investment if successful. If the mine is a bust, the entire investment is worthless. Your friend estimates the chance of success is only 20%. If you had the money, how much would you invest? | B15: 64 | C15: 132 | D15: 2.0625 | E15: 0.50396825
A16: sum | B16: 66 | C16: 1833 | D16: 27.772727 | E16: 49.809091
A19: ANOVA
A20: Source of Variation | B20: SS | C20: df | D20: MS | E20: F | F20: P-value | G20: F crit
A21: Between Groups | B21: 39685.479 | C21: 11 | D21: 3607.7709 | E21: 732.18789 | F21: 0 | G21: 1.8012206
A22: Within Groups | B22: 3749.7392 | C22: 761 | D22: 4.927384
A24: Total | B24: 43435.219 | C24: 772

Sheet Sheet1
A1: Age | B1: age | C1: Income(Per Month) | D1: In general, how would your best friend describe you as a risk taker? | E1: You are on a TV game show and can choose one of the following; which would you take? | F1: You have just finished saving for a “once-in-a-lifetime” vacation. Three weeks before you plan to leave, you lose your job. You would: | G1: If you unexpectedly received $20,000 to invest, what would you do? | H1: In terms of experience, how comfortable are you investing in stocks or stock mutual funds? | I1: When you think of the word “risk,” which of the following words comes to mind first? | J1: Some experts are predicting prices of assets such as gold, jewels, collectibles, and real estate (hard assets) to increase in value; bond prices may fall, however, experts tend to agree that government bonds are relatively safe. Most of your investment assets are now in high-interest government bonds. What would you do? | K1: Given the best and worst case returns of the four investment choices below, which would you prefer? | L1: In addition to whatever you own, you have been given $1,000. You are now asked to choose between: | M1: In addition to whatever you own, you have been given $2,000. You are now asked to choose between | N1: Suppose a relative left you an inheritance of $100,000, stipulating in the will that you invest ALL the money in ONE of the following choices. Which one would you select? | O1: If you had to invest $20,000, which of the following investment choices would you find most appealing? | P1: Your trusted friend and neighbor, an experienced geologist, is putting together a group of investors to fund an exploratory gold mining venture. The venture could pay back 50 to 100 times the investment if successful. If the mine is a bust, the entire investment is worthless. Your friend estimates the chance of success is only 20%. If you had the money, how much would you invest? | Q1: sum
A3: 31-40 | B3: Female | C3: <10k-20k | D3: 3 | E3: 2 | F3: 2 | G3: 2 | H3: 2 | I3: 2 | J3: 2 | K3: 2 | L3: 3 | M3: 3 | N3: 3 | O3: 2 | P3: 2 | Q3: =SUM(D3:P3) -> 30
A4: <18-30 | B4: Female | C4: <10k-20k | D4: 4 | E4: 4 | F4: 2 | G4: 1 | H4: 1 | I4: 3 | J4: 1 | K4: 1 | L4: 3 | M4: 1 | N4: 1 | O4: 3 | P4: 2 | Q4: =SUM(D4:P4) -> 27
A5: <18-30 | B5: Female | C5: <10k-20k | D5: 3 | E5: 3 | F5: 2 | G5: 3 | H5: 2 | I5: 3 | J5: 2 | K5: 3 | L5: 3 | M5: 3 | N5: 4 | O5: 2 | P5: 2 | Q5: =SUM(D5:P5) -> 35
A6: <18-30 | B6: Female | C6: 51k-60k> | D6: 3 | E6: 4 | F6: 3 | G6: 3 | H6: 3 | I6: 2 | J6: 3 | K6: 1 | L6: 1 | M6: 3 | N6: 1 | O6: 1 | P6: 2 | Q6: =SUM(D6:P6) -> 30
A7: <18-30 | B7: Female | C7: 51k-60k> | D7: 3 | E7: 4 | F7: 3 | G7: 2 | H7: 3 | I7: 2 | J7: 2 | K7: 1 | L7: 1 | M7: 3 | N7: 1 | O7: 1 | P7: 2 | Q7: =SUM(D7:P7) -> 28
A8: <18-30 | B8: Female | C8: <10k-20k | D8: 4 | E8: 2 | F8: 3 | G8: 2 | H8: 3 | I8: 2 | J8: 2 | K8: 1 | L8: 1 | M8: 3 | N8: 1 | O8: 2 | P8: 2 | Q8: =SUM(D8:P8) -> 28
A9: <18-30 | B9: Female | C9: <10k-20k | D9: 4 | E9: 2 | F9: 3 | G9: 2 | H9: 3 | I9: 2 | J9: 2 | K9: 1 | L9: 1 | M9: 3 | N9: 1 | O9: 2 | P9: 2 | Q9: =SUM(D9:P9) -> 28
A10: <18-30 | B10: Female | C10: <10k-20k | D10: 4 | E10: 2 | F10: 3 | G10: 2 | H10: 3 | I10: 2 | J10: 1 | K10: 1 | L10: 3 | M10: 1 | N10: 2 | O10: 2 | P10: 2 | Q10: =SUM(D10:P10) -> 28
A11: <18-30 | B11: Female | C11: <10k-20k | D11: 2 | E11: 1 | F11: 1 | G11: 1 | H11: 2 | I11: 2 | J11: 2 | K11: 3 | L11: 3 | M11: 1 | N11: 1 | O11: 1 | P11: 2 | Q11: =SUM(D11:P11) -> 22
A12: <18-30 | B12: Female | C12: <10k-20k | D12: 4 | E12: 2 | F12: 2 | G12: 2 | H12: 2 | I12: 3 | J12: 2 | K12: 2 | L12: 1 | M12: 3 | N12: 2 | O12: 2 | P12: 2 | Q12: =SUM(D12:P12) -> 29
A13: 31-40 | B13: Female | C13: 21k-40k | D13: 3 | E13: 1 | F13: 2 | G13: 1 | H13: 1 | I13: 2 | J13: 1 | K13: 1 | L13: 1 | M13: 1 | N13: 2 | O13: 2 | P13: 1 | Q13: =SUM(D13:P13) -> 19
A14: 31-40 | B14: Female | C14: 21k-40k | D14: 3 | E14: 1 | F14: 2 | G14: 1 | H14: 1 | I14: 2 | J14: 2 | K14: 1 | L14: 3 | M14: 1 | N14: 2 | O14: 2 | P14: 2 | Q14: =SUM(D14:P14) -> 23
... A32: <18-30 | B32: Female | C32: <10k-20k | D32: 4 | E32: 1 | F32: 3 | G32: 1 | H32: 1 | I32: 3 | J32: 2 | K32: 2 | L32: 3 | M32: 1 | N32: 1 | O32: 1 | P32: 2 | Q32: =SUM(D32:P32) -> 25
A33: <18-30 | B33: Female | C33: <10k-20k | Q33: =SUM(D33:P33) -> 0
A34: <18-30 | B34: Male | C34: <10k-20k | D34: 3 | E34: 2 | F34: 2 | G34: 2 | H34: 2 | I34: 2 | J34: 2 | K34: 2 | L34: 3 | M34: 3 | N34: 2 | O34: 2 | P34: 2 | Q34: =SUM(D34:P34) -> 29
A35: <18-30 | B35: Male | C35: <10k-20k | D35: 3 | E35: 1 | F35: 2 | G35: 2 | H35: 2 | I35: 2 | J35: 2 | K35: 2 | L35: 1 | M35: 3 | N35: 2 | O35: 2 | P35: 2 | Q35: =SUM(D35:P35) -> 26
A36: <18-30 | B36: Male | C36: <10k-20k | D36: 3 | E36: 1 | F36: 2 | G36: 2 | H36: 2 | I36: 2 | J36: 2 | K36: 2 | L36: 3 | M36: 3 | N36: 2 | O36: 2 | P36: 2 | Q36: =SUM(D36:P36) -> 28
A37: <18-30 | B37: Male | C37: <10k-20k | D37: 3 | E37: 1 | F37: 2 | G37: 3 | H37: 1 | I37: 2 | J37: 1 | K37: 3 | L37: 3 | M37: 3 | N37: 4 | O37: 2 | P37: 2 | Q37: =SUM(D37:P37) -> 30
A38: <18-30 | B38: Male | C38: <10k-20k | D38: 4 | E38: 1 | F38: 3 | G38: 1 | H38: 3 | I38: 3 | J38: 3 | K38: 3 | L38: 1 | M38: 1 | N38: 3 | O38: 2 | P38: 2 | Q38: =SUM(D38:P38) -> 30
A39: <18-30 | B39: Male | C39: <10k-20k | D39: 1 | E39: 2 | F39: 2 | G39: 1 | H39: 2 | I39: 2 | J39: 2 | K39: 2 | L39: 3 | M39: 3 | N39: 3 | O39: 2 | P39: 2 | Q39: =SUM(D39:P39) -> 27
A40: <18-30 | B40: Male | C40: <10k-20k | D40: 3 | E40: 1 | F40: 2 | G40: 3 | H40: 2 | I40: 2 | J40: 2 | K40: 2 | L40: 1 | M40: 1 | N40: 2 | O40: 2 | P40: 2 | Q40: =SUM(D40:P40) -> 25
A41: <18-30 | B41: Male | C41: <10k-20k | D41: 3 | E41: 2 | F41: 2 | G41: 2 | H41: 2 | I41: 2 | J41: 2 | K41: 2 | L41: 1 | M41: 1 | N41: 2 | O41: 2 | P41: 2 | Q41: =SUM(D41:P41) -> 25
A42: <18-30 | B42: Male | C42: <10k-20k | D42: 3 | E42: 3 | F42: 3 | G42: 3 | H42: 3 | I42: 4 | J42: 4 | K42: 3 | L42: 3 | M42: 3 | N42: 3 | O42: 2 | P42: 2 | Q42: =SUM(D42:P42) -> 39
A43: 31-40 | B43: Male | C43: 41k-60k | D43: 3 | E43: 1 | F43: 1 | G43: 3 | H43: 2 | I43: 1 | J43: 1 | K43: 1 | L43: 1 | M43: 3 | N43: 1 | O43: 1 | P43: 1 | Q43: =SUM(D43:P43) -> 20
A44: <18-30 | B44: Male | C44: <10k-20k | D44: 3 | E44: 4 | F44: 3 | G44: 2 | H44: 2 | I44: 4 | J44: 1 | K44: 1 | L44: 1 | M44: 3 | N44: 3 | O44: 2 | P44: 1 | Q44: =SUM(D44:P44) -> 30
A45: <18-30 | B45: Male | C45: <10k-20k | D45: 3 | E45: 3 | F45: 2 | G45: 2 | H45: 2 | I45: 2 | J45: 2 | K45: 3 | L45: 3 | M45: 3 | N45: 2 | O45: 2 | P45: 2 | Q45: =SUM(D45:P45) -> 31
... A56: <18-30 | B56: Male | C56: <10k-20k | D56: 1 | E56: 1 | F56: 1 | G56: 1 | H56: 1 | I56: 1 | J56: 1 | K56: 2 | L56: 1 | M56: 1 | N56: 2 | O56: 1 | P56: 1 | Q56: =SUM(D56:P56) -> 15
A57: <18-30 | B57: Male | C57: <10k-20k | E57: 2 | F57: 4 | G57: 2 | H57: 2 | I57: 2 | J57: 2 | K57: 3 | L57: 1 | M57: 3 | N57: 1 | O57: 2 | P57: 3 | Q57: =SUM(D57:P57) -> 27
A58: <18-30 | B58: Male | C58: 21k-40k | D58: 4 | E58: 2 | F58: 2 | G58: 1 | H58: 2 | I58: 2 | J58: 2 | K58: 2 | L58: 1 | M58: 1 | N58: 1 | O58: 2 | P58: 2 | Q58: =SUM(D58:P58) -> 24
A59: 41-50 | B59: Male | C59: 21k-40k | D59: 3 | E59: 2 | F59: 2 | G59: 1 | H59: 2 | I59: 2 | J59: 3 | K59: 2 | L59: 3 | M59: 3 | N59: 3 | O59: 2 | P59: 2 | Q59: =SUM(D59:P59) -> 30
A60: <18-30 | B60: Male | C60: <10k-20k | D60: 1 | E60: 1 | F60: 3 | G60: 1 | H60: 1 | I60: 4 | J60: 2 | K60: 1 | L60: 1 | M60: 3 | N60: 1 | O60: 1 | P60: 1 | Q60: =SUM(D60:P60) -> 21
A61: <18-30 | B61: Male | C61: 21k-40k | D61: 2 | E61: 3 | F61: 2 | G61: 3 | H61: 2 | I61: 3 | J61: 4 | K61: 2 | L61: 3 | M61: 1 | N61: 1 | O61: 3 | P61: 1 | Q61: =SUM(D61:P61) -> 30
A62: 51->60 | B62: Male | C62: 41k-60k | D62: 4 | E62: 4 | F62: 3 | G62: 2 | H62: 3 | I62: 4 | J62: 3 | K62: 4 | L62: 3 | M62: 1 | N62: 4 | O62: 3 | P62: 4 | Q62: =SUM(D62:P62) -> 42
A63: 51->60 | B63: Male | C63: 41k-60k | D63: 3 | E63: 2 | F63: 3 | G63: 1 | H63: 2 | I63: 3 | J63: 3 | K63: 2 | L63: 3 | M63: 1 | O63: 2 | P63: 3 | Q63: =SUM(D63:P63) -> 28
A64: 41-50 | B64: Male | C64: 41k-60k | D64: 1 | E64: 3 | F64: 3 | G64: 1 | H64: 2 | I64: 4 | J64: 3 | K64: 2 | L64: 3 | M64: 3 | N64: 3 | O64: 2 | P64: 4 | Q64: =SUM(D64:P64) -> 34
A65: 41-50 | B65: Male | C65: 21k-40k | D65: 3 | E65: 2 | G65: 1 | H65: 1 | I65: 2 | J65: 3 | K65: 2 | L65: 3 | M65: 1 | N65: 3 | O65: 2 | P65: 1 | Q65: =SUM(D65:P65) -> 24
A66: <18-30 | B66: Male | C66: 21k-40k | F66: 1 | G66: 1 | H66: 1 | I66: 1 | J66: 1 | Q66: =SUM(D66:P66) -> 5
A67: <18-30 | B67: Male | C67: <10k-20k | D67: 4 | E67: 2 | F67: 2 | G67: 2 | H67: 1 | I67: 2 | J67: 1 | K67: 2 | L67: 3 | M67: 3 | N67: 3 | O67: 2 | P67: 1 | Q67: =SUM(D67:P67) -> 28
A68: <18-30 | B68: Male | C68: >60k | D68: 4 | E68: 4 | F68: 1 | G68: 2 | H68: 3 | I68: 3 | J68: 3 | K68: 4 | L68: 3 | M68: 3 | N68: 3 | O68: 2 | P68: 2 | Q68: =SUM(D68:P68) -> 37

Sheet Sheet3
A1: Age | B1: Income(Per Month) | C1: In general, how would your best friend describe you as a risk taker? | D1: You are on a TV game show and can choose one of the following; which would you take? | E1: You have just finished saving for a “once-in-a-lifetime” vacation. Three weeks before you plan to leave, you lose your job. You would: | F1: If you unexpectedly received $20,000 to invest, what would you do? | G1: In terms of experience, how comfortable are you investing in stocks or stock mutual funds? | H1: When you think of the word “risk,” which of the following words comes to mind first? | I1: Some experts are predicting prices of assets such as gold, jewels, collectibles, and real estate (hard assets) to increase in value; bond prices may fall, however, experts tend to agree that government bonds are relatively safe. Most of your investment assets are now in high-interest government bonds. What would you do? | J1: Given the best and worst case returns of the four investment choices below, which would you prefer? | K1: In addition to whatever you own, you have been given $1,000. You are now asked to choose between: | L1: In addition to whatever you own, you have been given $2,000. You are now asked to choose between | M1: Suppose a relative left you an inheritance of $100,000, stipulating in the will that you invest ALL the money in ONE of the following choices. Which one would you select? | N1: If you had to invest $20,000, which of the following investment choices would you find most appealing? | O1: Your trusted friend and neighbor, an experienced geologist, is putting together a group of investors to fund an exploratory gold mining venture. The venture could pay back 50 to 100 times the investment if successful. If the mine is a bust, the entire investment is worthless. Your friend estimates the chance of success is only 20%. If you had the money, how much would you invest? | P1: sum
A3: 31-40 | B3: 000-20000 | C3: 3 | D3: 2 | E3: 2 | F3: 2 | G3: 2 | H3: 2 | I3: 2 | J3: 2 | K3: 3 | L3: 3 | M3: 3 | N3: 2 | O3: 2
A4: <18-30 | B4: 000-20000 | C4: 4 | D4: 4 | E4: 2 | F4: 1 | G4: 1 | H4: 3 | I4: 1 | J4: 1 | K4: 3 | L4: 1 | M4: 1 | N4: 3 | O4: 2 | P4: =SUM(C4:O4) -> 27
A5: <18-30 | B5: 000-20000 | C5: 3 | D5: 3 | E5: 2 | F5: 3 | G5: 2 | H5: 3 | I5: 2 | J5: 3 | K5: 3 | L5: 3 | M5: 4 | N5: 2 | O5: 2 | P5: =SUM(C5:O5) -> 35
A6: <18-30 | B6: 51000-60000 | C6: 3 | D6: 4 | E6: 3 | F6: 3 | G6: 3 | H6: 2 | I6: 3 | J6: 1 | K6: 1 | L6: 3 | M6: 1 | N6: 1 | O6: 2 | P6: =SUM(C6:O6) -> 30
A7: <18-30 | B7: 51000-60000 | C7: 3 | D7: 4 | E7: 3 | F7: 2 | G7: 3 | H7: 2 | I7: 2 | J7: 1 | K7: 1 | L7: 3 | M7: 1 | N7: 1 | O7: 2 | P7: =SUM(C7:O7) -> 28
A8: <18-30 | B8: 000-20000 | C8: 4 | D8: 2 | E8: 3 | F8: 2 | G8: 3 | H8: 2 | I8: 2 | J8: 1 | K8: 1 | L8: 3 | M8: 1 | N8: 2 | O8: 2 | P8: =SUM(C8:O8) -> 28
A9: <18-30 | B9: 000-20000 | C9: 4 | D9: 2 | E9: 3 | F9: 2 | G9: 3 | H9: 2 | I9: 2 | J9: 1 | K9: 1 | L9: 3 | M9: 1 | N9: 2 | O9: 2 | P9: =SUM(C9:O9) -> 28
A10: <18-30 | B10: 000-20000 | C10: 4 | D10: 2 | E10: 3 | F10: 2 | G10: 3 | H10: 2 | I10: 1 | J10: 1 | K10: 3 | L10: 1 | M10: 2 | N10: 2 | O10: 2 | P10: =SUM(C10:O10) -> 28
A11: <18-30 | B11: 000-20000 | C11: 2 | D11: 1 | E11: 1 | F11: 1 | G11: 2 | H11: 2 | I11: 2 | J11: 3 | K11: 3 | L11: 1 | M11: 1 | N11: 1 | O11: 2 | P11: =SUM(C11:O11) -> 22
A12: <18-30 | B12: 000-20000 | C12: 4 | D12: 2 | E12: 2 | F12: 2 | G12: 2 | H12: 3 | I12: 2 | J12: 2 | K12: 1 | L12: 3 | M12: 2 | N12: 2 | O12: 2 | P12: =SUM(C12:O12) -> 29
A13: 31-40 | B13: 21000-40000 | C13: 3 | D13: 1 | E13: 2 | F13: 1 | G13: 1 | H13: 2 | I13: 1 | J13: 1 | K13: 1 | L13: 1 | M13: 2 | N13: 2 | O13: 1 | P13: =SUM(C13:O13) -> 19
A14: 31-40 | B14: 21000-40000 | C14: 3 | D14: 1 | E14: 2 | F14: 1 | G14: 1 | H14: 2 | I14: 2 | J14: 1 | K14: 3 | L14: 1 | M14: 2 | N14: 2 | O14: 2 | P14: =SUM(C14:O14) -> 23
A15: 51->60 | B15: 21000-40000 | C15: 2 | D15: 3 | E15: 3 | F15: 2 | G15: 2 | H15: 3 | I15: 3 | J15: 2 | K15: 1 | L15: 3 | M15: 3 | N15: 1 | O15: 3 | P15: =SUM(C15:O15) -> 31
... A68: <18-30 | B68: 60000-100000 | C68: 4 | D68: 4 | E68: 1 | F68: 2 | G68: 3 | H68: 3 | I68: 3 | J68: 4 | K68: 3 | L68: 3 | M68: 3 | N68: 2 | O68: 2 | P68: =SUM(C68:O68) -> 37

Sheet Sheet4
A1: Income(Per Month)
A3: 000-20000 | B3: =SUM(Sheet3!C3:O3) -> 30
A4: 000-20000 | B4: =SUM(Sheet3!C4:O4) -> 27
A5: 000-20000 | B5: =SUM(Sheet3!C5:O5) -> 35
A6: 51000-60000 | B6: =SUM(Sheet3!C6:O6) -> 30
A7: 51000-60000 | B7: =SUM(Sheet3!C7:O7) -> 28
A8: 000-20000 | B8: =SUM(Sheet3!C8:O8) -> 28
A9: 000-20000 | B9: =SUM(Sheet3!C9:O9) -> 28
A10: 000-20000 | B10: =SUM(Sheet3!C10:O10) -> 28
A11: 000-20000 | B11: =SUM(Sheet3!C11:O11) -> 22
A12: 000-20000 | B12: =SUM(Sheet3!C12:O12) -> 29
A13: 21000-40000 | B13: =SUM(Sheet3!C13:O13) -> 19
A14: 21000-40000 | B14: =SUM(Sheet3!C14:O14) -> 23
... A68: 60000-100000 | B68: =SUM(Sheet3!C68:O68) -> 37
